Workbook

Sheet Registration
A1: REGISTRATION MODULE - TEST EXECUTION SPECIFICATION
A2: Website: Automation Test Store | Execution Type: Manual Testing
A3: Test Case ID | B3: Test Scenario | C3: Test Steps | D3: Test Data | E3: Expected Result | F3: Actual Result | G3: Status
A4: Rg_01 | B4: Create a new user account with valid details | C4: 1. Click 'Login or Register'. 2. Select 'Register account' and click 'Continue'. 3. Fill in all mandatory fields. 4. Check Privacy policy. 5. Click 'Continue'. | D4: First Name, Last Name, Email, Username, Password | E4: User is redirected to 'Account Created' page; success message is displayed. | F4: User redirected to 'Your Account Has Been Created!' page with success confirmation message. | G4: Pass
A5: Rg_02 | B5: Verify duplicate Username error validation | C5: 1. Navigate to Registration page. 2. Enter an already registered username. 3. Fill all other mandatory fields. 4. Click 'Continue'. | D5: Pre-existing Username in DB | E5: 'Username is already taken' error message is displayed. | F5: Error message 'Error: This login name is not available' displayed. | G5: Pass
A6: Rg_03 | B6: Verify mandatory field validation (Empty Password) | C6: 1. Navigate to Registration page. 2. Fill all mandatory fields except 'Password'. 3. Click 'Continue'. | D6: Valid data, empty Password | E6: Error message 'Password must be between 4 and 20 characters' is displayed. | F6: Error message 'Password must be between 4 and 20 characters!' displayed. | G6: Pass
A7: Rg_04 | B7: Verify registration with invalid Email format | C7: 1. Navigate to Registration page. 2. Enter invalid email (e.g. user@domain). 3. Fill remaining mandatory fields. 4. Click 'Continue'. | D7: Invalid Email format | E7: Error message 'E-Mail Address does not appear to be valid!' is displayed. | F7: Error message 'E-Mail Address does not appear to be valid!' displayed. | G7: Pass
A8: Rg_05 | B8: Verify Password and Confirm Password mismatch | C8: 1. Navigate to Registration page. 2. Enter Password and different Confirm Password. 3. Click 'Continue'. | D8: Password: Pass123, Confirm: Pass456 | E8: Error message 'Password confirmation does not match password!' is displayed. | F8: Error message 'Password confirmation does not match password!' displayed. | G8: Pass
A9: Rg_06 | B9: Verify Privacy Policy unchecked state | C9: 1. Fill all required fields in Registration form. 2. Keep 'Privacy Policy' checkbox unchecked. 3. Click 'Continue'. | D9: Valid registration data | E9: Error message 'Warning: You must agree to the Privacy Policy!' is displayed. | F9: Error message 'Error: You must agree to the Privacy Policy!' displayed. | G9: Pass
A10: Rg_07 | B10: Verify Registration with First Name shorter than min length | C10: 1. Enter 1-character First Name. 2. Fill other fields properly. 3. Click 'Continue'. | D10: First Name: 'A' | E10: Error message 'First Name must be between 1 and 32 characters!' is displayed. | F10: Error message 'First Name must be between 1 and 32 characters!' displayed. | G10: Pass
A11: Rg_08 | B11: Verify Registration with First Name exceeding max length | C11: 1. Enter 33-character First Name. 2. Fill other fields properly. 3. Click 'Continue'. | D11: 33 alpha chars string | E11: Validation error regarding max length limit for First Name is displayed. | F11: Error message 'First Name must be between 1 and 32 characters!' displayed. | G11: Pass
A12: Rg_09 | B12: Verify Registration with duplicate Email address | C12: 1. Enter an email address that already exists in DB. 2. Fill required fields. 3. Click 'Continue'. | D12: Existing Email ID | E12: Error message 'Warning: E-Mail Address is already registered!' is displayed. | F12: Error message 'Error: E-Mail Address is already registered!' displayed. | G12: Pass
A13: Rg_10 | B13: Verify Telephone field numeric-only validation | C13: 1. Enter non-numeric characters in Telephone field. 2. Fill other fields. 3. Click 'Continue'. | D13: Telephone: 'ABCDE' | E13: Appropriate error message for invalid phone format is displayed. | F13: Form submitted without showing phone format validation error. | G13: Fail
A14: Rg_11 | B14: Verify subscribing to Newsletter during registration | C14: 1. Fill registration form. 2. Select 'Yes' for Newsletter option. 3. Click 'Continue'. | D14: Valid registration data | E14: Account created and user receives newsletter confirmation email. | F14: Account created and newsletter status set to subscribed in profile. | G14: Pass
... A23: Rg_20 | B23: Verify Account creation email notification trigger | C23: 1. Complete successful user account registration. | D23: Valid dynamic email | E23: Welcome/activation email is sent to registered email address. | F23: Welcome email received in registered inbox with account confirmation details. | G23: Pass

Sheet Authentication
A1: AUTHENTICATION MODULE - TEST EXECUTION SPECIFICATION
A2: Website: Automation Test Store | Execution Type: Manual Testing
A3: Test Case ID | B3: Test Scenario | C3: Test Steps | D3: Test Data | E3: Expected Result | F3: Actual Result | G3: Status
A4: Login_01 | B4: Login with valid credentials | C4: 1. Click 'Login or Register'. 2. Enter valid username and password. 3. Click 'Login'. | D4: valid_username, valid_password | E4: 'Welcome back valid_username' is displayed. User is logged in. | F4: 'Welcome back [Name]' banner displayed in My Account dashboard. | G4: Pass
A5: Login_02 | B5: Login with invalid credentials | C5: 1. Click 'Login or Register'. 2. Enter invalid username or password. 3. Click 'Login'. | D5: invalid_username, invalid_password | E5: Error message 'Error: Incorrect Login or password' is displayed. | F5: Error message 'Error: Incorrect login or password provided.' displayed. | G5: Pass
A6: Login_03 | B6: Password reset functionality | C6: 1. Navigate to Login page. 2. Click 'Forgot your password?'. 3. Enter email and click 'Continue'. | D6: Valid registered email | E6: 'Success: A new password has been sent...' message is displayed. | F6: Success message 'Success: Password reset link sent to your e-mail address.' displayed. | G6: Pass
A7: Login_04 | B7: Login with blank credentials | C7: 1. Leave username and password blank. 2. Click 'Login'. | D7: Empty fields | E7: Validation message prompting required fields is displayed. | F7: Error message 'Error: Incorrect login or password provided.' displayed. | G7: Pass
A8: Login_05 | B8: Login with uppercase Password (Case sensitivity check) | C8: 1. Enter valid username. 2. Enter valid password in ALL CAPS. 3. Click 'Login'. | D8: valid_username, UPPERCASE_PASS | E8: Login fails due to password case sensitivity. | F8: Login attempt failed with authentication error message. | G8: Pass
A9: Login_06 | B9: Account lockout after multiple failed attempts | C9: 1. Attempt login with invalid password 5 consecutive times. | D9: valid_username, wrong_password | E9: Account is temporarily locked with warning message displayed. | F9: No account lockout triggered after 5 failed login attempts. | G9: Fail
A10: Login_07 | B10: Password reset with non-registered Email | C10: 1. Click 'Forgot your password?'. 2. Enter email not in database. 3. Click 'Continue'. | D10: nonregistered@email.com | E10: Error message 'Warning: The E-Mail Address was not found!' is displayed. | F10: Error message 'Error: The E-Mail Address was not found in our records' displayed. | G10: Pass
A11: Login_08 | B11: Verify 'Remember Me' checkbox functionality | C11: 1. Enter valid credentials. 2. Check 'Remember Me'. 3. Click 'Login'. 4. Close and re-open browser. | D11: Valid credentials | E11: User remains logged in without re-entering credentials. | F11: 'Remember Me' option not available on login form. | G11: Fail
A12: Login_09 | B12: Verify Logout functionality | C12: 1. Log into the application. 2. Click 'Logout' link/button. | D12: Logged-in session | E12: User is logged out and redirected to Login/Home page. | F12: User logged out successfully and redirected to Account Logout page. | G12: Pass
A13: Login_10 | B13: Verify session expiration after inactivity | C13: 1. Log in and remain idle for defined session timeout period. 2. Click any internal link. | D13: Idle session | E13: User is automatically logged out and asked to re-authenticate. | F13: Session expired after idle period; user redirected to login page on click. | G13: Pass
A14: Login_11 | B14: Verify browser Back button after Logout | C14: 1. Log out from account. 2. Click browser's 'Back' button. | D14: Post-logout state | E14: User cannot access protected account pages without re-logging in. | F14: Cached account page renders briefly before redirecting to login page. | G14: Fail
... A23: Login_20 | B23: Verify Login page response under network latency | C23: 1. Simulate slow 3G network condition. 2. Submit login request. | D23: Valid credentials, network throttled | E23: Spinner/loader appears and login completes without timing out prematurely. | F23: Login completed successfully without timing out under slow network condition. | G23: Pass

Sheet Search
A1: SEARCH MODULE - TEST EXECUTION SPECIFICATION
A2: Website: Automation Test Store | Execution Type: Manual Testing
A3: Test Case ID | B3: Test Scenario | C3: Test Steps | D3: Test Data | E3: Expected Result | F3: Actual Result | G3: Status
A4: Search_01 | B4: Search for a valid product | C4: 1. Type exact product name in search bar. 2. Click search icon. | D4: Total Moisture Facial Cream | E4: Search results page displays the specified product. | F4: Product 'Total Moisture Facial Cream' displayed in search results. | G4: Pass
A5: Search_02 | B5: Search for non-existing product | C5: 1. Type non-existent product keyword. 2. Click search icon. | D5: Invalidproduct123 | E5: Message 'There is no product that matches the search criteria' is displayed. | F5: Message 'There is no product that matches the search criteria.' displayed. | G5: Pass
A6: Search_03 | B6: Search using partial product name | C6: 1. Type partial keyword in search bar. 2. Click search icon. | D6: Moisture | E6: All products containing 'Moisture' in title are listed. | F6: List of products containing 'Moisture' displayed. | G6: Pass
A7: Search_04 | B7: Search with blank search field | C7: 1. Leave search input field blank. 2. Click search icon. | D7: Empty string | E7: Page prompts user to enter search criteria or lists all categories. | F7: Search results page displays with prompt to enter search criteria. | G7: Pass
A8: Search_05 | B8: Search with case-insensitive keywords | C8: 1. Type product name in lower/UPPER case. 2. Click search icon. | D8: total moisture facial cream | E8: Matching products are returned regardless of letter casing. | F8: Product returned successfully regardless of lower/UPPER casing. | G8: Pass
A9: Search_06 | B9: Search with special characters | C9: 1. Enter special characters in search box. 2. Click search icon. | D9: @#$%^&* | E9: System handles input safely and returns zero results message. | F9: Zero search results message displayed safely without layout/script error. | G9: Pass
A10: Search_07 | B10: Search filtering by Category | C10: 1. Select sub-category from search dropdown. 2. Enter keyword and search. | D10: Category: Skincare, Key: Cream | E10: Results are filtered strictly to selected category. | F10: Results filtered accurately to selected category 'Skincare'. | G10: Pass
A11: Search_08 | B11: Search in product description checkbox | C11: 1. Enter keyword present only in description. 2. Check 'Search in product descriptions'. 3. Click search. | D11: Description keyword | E11: Relevant products containing term in description are displayed. | F11: Matching products containing description term displayed. | G11: Pass
A12: Search_09 | B12: Verify Auto-complete search suggestions | C12: 1. Type first 3 letters of product name. | D12: Tot | E12: Dropdown overlay shows matching live auto-suggestions. | F12: Auto-complete suggestion dropdown not implemented on search bar. | G12: Fail
A13: Search_10 | B13: Search result pagination | C13: 1. Search for keyword matching > 20 products. 2. Navigate through page numbers. | D13: Popular product term | E13: Pagination works correctly showing split product listings. | F13: Pagination controls display and navigate across result pages. | G13: Pass
A14: Search_11 | B14: Sort search results by Price (Low to High) | C14: 1. Execute search. 2. Select Sort by: 'Price (Low > High)'. | D14: Valid search query | E14: Products are reordered accurately by price ascending. | F14: Products reordered accurately by price in ascending order. | G14: Pass
... A23: Search_20 | B23: Search performance with large result set | C23: 1. Enter common letter like 'a'. 2. Submit search query. | D23: Keyword: 'a' | E23: Results page renders within acceptable time frame without breaking layout. | F23: Search results page rendered in under 1.2 seconds without layout break. | G23: Pass

Sheet Cart
A1: CART MODULE - TEST EXECUTION SPECIFICATION
A2: Website: Automation Test Store | Execution Type: Manual Testing
A3: Test Case ID | B3: Test Scenario | C3: Test Steps | D3: Test Data | E3: Expected Result | F3: Actual Result | G3: Status
A4: Cart_01 | B4: Add single product to cart | C4: 1. Click on any product on homepage. 2. Click 'Add to Cart'. | D4: Featured Product | E4: Cart counter increments by 1; product appears in cart. | F4: Product added to cart and cart badge updated. | G4: Pass
A5: Cart_02 | B5: Update product quantity in cart | C5: 1. Open shopping cart. 2. Change quantity value. 3. Click 'Update'. | D5: Quantity = 2 | E5: Total price updates dynamically based on new quantity. | F5: Quantity updated to 2 and subtotal re-calculated accurately. | G5: Pass
A6: Cart_03 | B6: Remove a product from cart | C6: 1. Navigate to shopping cart. 2. Click 'Remove' icon next to item. | D6: Product in cart | E6: Item is removed, total price updates, empty cart message shown if empty. | F6: Item removed from cart table and cart total updated. | G6: Pass
A7: Cart_04 | B7: Add product to cart with option selection | C7: 1. Choose product with required options (e.g. Size/Color). 2. Click 'Add to Cart'. | D7: Size: Medium, Color: Blue | E7: Product added with correct selected option attributes. | F7: Product added to cart reflecting selected options. | G7: Pass
A8: Cart_05 | B8: Add out of stock product to cart | C8: 1. Navigate to out-of-stock product page. 2. Check 'Add to Cart' availability. | D8: Out of stock item | E8: 'Add to Cart' button is disabled or error alert is shown. | F8: Out of stock item allowed addition to cart without warning. | G8: Fail
A9: Cart_06 | B9: Verify cart persistence across session | C9: 1. Add items to cart as logged-in user. 2. Log out and log back in. | D9: User account with items | E9: Items remain in cart across user re-authentication. | F9: Cart items persisted upon user re-login. | G9: Pass
A10: Cart_07 | B10: Verify cart updating on quantity zero input | C10: 1. Go to cart page. 2. Set item quantity to 0. 3. Click 'Update'. | D10: Quantity = 0 | E10: Item is automatically removed from cart. | F10: Item removed automatically when quantity updated to 0. | G10: Pass
A11: Cart_08 | B11: Verify max quantity threshold in cart | C11: 1. Set item quantity to exceeds inventory (e.g. 99999). 2. Click 'Update'. | D11: Quantity = 99999 | E11: Warning message regarding available stock limit appears. | F11: Warning message displayed regarding stock limit. | G11: Pass
A12: Cart_09 | B12: Apply valid Coupon code in cart | C12: 1. Open shopping cart. 2. Enter valid discount code. 3. Click 'Apply Coupon'. | D12: Coupon: DISCOUNT10 | E12: Discount value is subtracted from order total. | F12: Coupon applied and discount deducted from total. | G12: Pass
A13: Cart_10 | B13: Apply invalid Coupon code in cart | C13: 1. Open shopping cart. 2. Enter expired/fake discount code. 3. Click 'Apply Coupon'. | D13: Coupon: INVALID99 | E13: Error message 'Warning: Coupon is either invalid or expired!' appears. | F13: Error message 'Error: Coupon is either invalid, expired or reached its usage limit!' displayed. | G13: Pass
A14: Cart_11 | B14: Apply Gift Certificate in cart | C14: 1. Open cart. 2. Enter valid Gift Voucher code. 3. Click 'Apply Voucher'. | D14: Voucher: GIFT50 | E14: Voucher balance is applied towards subtotal. | F14: Gift voucher applied successfully to order total. | G14: Pass
... A23: Cart_20 | B23: Verify Continue Shopping button in cart | C23: 1. Open cart page. 2. Click 'Continue Shopping' button. | D23: N/A | E23: User is redirected to homepage or previous product category. | F23: User redirected back to store shopping page. | G23: Pass

Sheet Checkout
A1: CHECKOUT MODULE - TEST EXECUTION SPECIFICATION
A2: Website: Automation Test Store | Execution Type: Manual Testing
A3: Test Case ID | B3: Test Scenario | C3: Test Steps | D3: Test Data | E3: Expected Result | F3: Actual Result | G3: Status
A4: Checkout_01 | B4: End-to-End checkout as Guest | C4: 1. Add product to cart and click 'Checkout'. 2. Select 'Guest Checkout' and click 'Continue'. 3. Fill billing details and click 'Confirm Order'. | D4: Guest Name, Address, Email | E4: User redirected to Success page with Order ID generated. | F4: Order completed successfully; redirected to success page with generated Order ID. | G4: Pass
A5: Checkout_02 | B5: Checkout as Registered returning user | C5: 1. Log in with registered user. 2. Proceed to checkout. 3. Select stored address and confirm order. | D5: Registered user account | E5: Order submitted smoothly utilizing pre-saved address. | F5: Checkout completed using pre-saved address. | G5: Pass
A6: Checkout_03 | B6: Register account during Checkout step | C6: 1. Add product and proceed to Checkout. 2. Select 'Register Account' radio option. 3. Fill details & complete checkout. | D6: New user details | E6: Account created and order processed in single workflow. | F6: Account created and order confirmed in single flow. | G6: Pass
A7: Checkout_04 | B7: Checkout with empty mandatory billing fields | C7: 1. Select Guest Checkout. 2. Leave mandatory address fields empty. 3. Click 'Continue'. | D7: Blank mandatory fields | E7: Inline error warnings highlight required billing fields. | F7: Validation warnings displayed highlighting required fields. | G7: Pass
A8: Checkout_05 | B8: Checkout with separate Shipping address | C8: 1. Uncheck 'My delivery and billing addresses are same'. 2. Fill distinct shipping address. 3. Proceed to confirm. | D8: Billing address != Shipping address | E8: Order confirmation reflects differing billing and shipping info. | F8: Order created reflecting distinct billing and shipping details. | G8: Pass
A9: Checkout_06 | B9: Verify Payment Method selection (Cash on Delivery) | C9: 1. Reach Payment Method step. 2. Select 'Cash on Delivery'. 3. Accept Terms & Conditions and continue. | D9: COD option | E9: Order confirmed with payment status marked as Pending/COD. | F9: Order confirmed with COD payment status. | G9: Pass
A10: Checkout_07 | B10: Verify Payment Method selection (Credit Card) | C10: 1. Reach Payment Method step. 2. Select Credit Card option. 3. Enter test card details and confirm. | D10: Test Credit Card info | E10: Payment processed successfully and order placed. | F10: Payment processed successfully in test mode and order placed. | G10: Pass
A11: Checkout_08 | B11: Verify Terms and Conditions checkbox requirement | C11: 1. Reach final checkout step. 2. Leave 'Terms & Conditions' unchecked. 3. Click 'Continue'. | D11: Unchecked T&C | E11: Warning popup 'You must agree to Terms & Conditions!' appears. | F11: Error message 'Error: You must agree to the Terms & Conditions!' displayed. | G11: Pass
A12: Checkout_09 | B12: Verify Order Summary review prior to confirmation | C12: 1. Navigate to final Checkout confirmation step. | D12: Cart items | E12: Summary lists correct item names, quantities, unit prices, tax, total. | F12: Order summary table accurately lists items, prices, taxes, and grand total. | G12: Pass
A13: Checkout_10 | B13: Verify Order confirmation Email generation | C13: 1. Complete successful checkout order. | D13: Valid user email | E13: Order confirmation email with details is delivered to user. | F13: Order confirmation email received with itemized invoice details. | G13: Pass
A14: Checkout_11 | B14: Verify Coupon code application at Checkout | C14: 1. Enter promo code in checkout discount box. 2. Click 'Apply'. | D14: Valid promo code | E14: Order summary total updates with discount applied. | F14: Order total updated with discount applied. | G14: Pass
... A23: Checkout_20 | B23: Verify Order history record updated post checkout | C23: 1. Complete checkout as registered user. 2. Navigate to 'My Account' > 'Order History'. | D23: Logged-in user order | E23: Newly created order appears at top of order history list. | F23: New order listed at top of user Order History with 'Pending' status. | G23: Pass

Sheet UI
A1: USER INTERFACE MODULE - TEST EXECUTION SPECIFICATION
A2: Website: Automation Test Store | Execution Type: Manual Testing
A3: Test Case ID | B3: Test Scenario | C3: Test Steps | D3: Test Data | E3: Expected Result | F3: Actual Result | G3: Status
A4: UI_01 | B4: Verify category Navigation from main menu | C4: 1. Locate Main Header Menu. 2. Click dynamic category link (e.g. Fragrance). | D4: Category Links | E4: Category page lists relevant products; breadcrumb updates. | F4: Category page loaded with products and breadcrumbs updated. | G4: Pass
A5: UI_02 | B5: Verify Breadcrumb navigation links | C5: 1. Navigate deep into product detail page. 2. Click middle link in breadcrumb bar. | D5: Breadcrumb path | E5: User is navigated directly to selected parent category page. | F5: Navigated directly to selected parent category upon clicking breadcrumb. | G5: Pass
A6: UI_03 | B6: Verify responsive layout on Mobile viewports | C6: 1. Resize browser width to mobile screen (e.g. 375px width). | D6: Mobile resolution | E6: Navigation collapses into hamburger menu; layout scales smoothly. | F6: Navigation collapsed into responsive mobile menu seamlessly. | G6: Pass
A7: UI_04 | B7: Verify responsive layout on Tablet viewports | C7: 1. Resize browser width to tablet screen (e.g. 768px width). | D7: Tablet resolution | E7: Layout adjusts columns appropriately without horizontal scrolling. | F7: Layout scaled cleanly without horizontal scrollbars. | G7: Pass
A8: UI_05 | B8: Verify main homepage Hero Banner slider carousel | C8: 1. Observe homepage main slider banner. 2. Click Next/Prev arrows or let auto-scroll. | D8: Banner Carousel | E8: Banner slides seamlessly to next promotional image. | F8: Banner carousel slides smoothly and controls respond correctly. | G8: Pass
A9: UI_06 | B9: Verify Footer social media links navigation | C9: 1. Scroll down to footer. 2. Click Facebook / Twitter social icons. | D9: Footer links | E9: Social media pages open correctly in new browser tabs. | F9: Social media links open official pages in new tabs. | G9: Pass
A10: UI_07 | B10: Verify 'Scroll to Top' button functionality | C10: 1. Scroll down to bottom of long page. 2. Click floating 'Scroll to Top' arrow. | D10: Bottom of page | E10: Page smoothly scrolls back to top header. | F10: Scroll to top button smoothly returned page to top header. | G10: Pass
A11: UI_08 | B11: Verify Product image zoom feature | C11: 1. Navigate to product details page. 2. Hover over or click product thumbnail. | D11: Product Image | E11: Enlarged high-resolution image zoom modal opens. | F11: High-resolution image modal opened upon clicking thumbnail. | G11: Pass
A12: UI_09 | B12: Verify Header contact number and email link display | C12: 1. Inspect header contact bar. 2. Click phone/email link. | D12: Header contact info | E12: Initiates call protocol or opens default mail client. | F12: Phone link triggers call protocol and email link opens mail client. | G12: Pass
A13: UI_10 | B13: Verify Broken links check across homepage | C13: 1. Run automated crawler or click key homepage links. | D13: Homepage elements | E13: All links return valid HTTP 200 responses without 404 errors. | F13: All tested header/footer links returned valid HTTP 200 responses. | G13: Pass
A14: UI_11 | B14: Verify Tooltip display on action buttons | C14: 1. Hover cursor over 'Add to Wishlist' / 'Compare' icons. | D14: Icon buttons | E14: Descriptive tooltip text appears near cursor. | F14: Tooltip text displays on hovering action icons. | G14: Pass
... A23: UI_20 | B23: Verify Cookie Consent banner display | C23: 1. Clear cookies and load homepage. | D23: Clean browser storage | E23: Cookie consent notification banner displays with Accept option. | F23: Cookie consent banner displayed at bottom of viewport. | G23: Pass

Sheet Dashboard
B2: AUTOMATION TEST STORE - MANUAL TESTING DASHBOARD
B3: Executive Test Execution Summary & Quality Metrics Report | Environment: Demo Web Store
B5: TOTAL TEST CASES | D5: PASSED | F5: FAILED | H5: PASS RATE %
B6: =SUM(C11:C16) -> 120 | D6: =SUM(D11:D16) -> 106 | F6: =SUM(E11:E16) -> 13 | H6: =D6/B6 -> 0.88333333
B9: MODULE EXECUTION BREAKDOWN
B10: Module Name | C10: Total Tests | D10: Passed | E10: Failed | F10: Blocked | G10: Pass Rate (%)
B11: Registration | C11: 20 | D11: 18 | E11: 2 | F11: 0 | G11: =D11/C11 -> 0.9
B12: Authentication | C12: 20 | D12: 17 | E12: 3 | F12: 0 | G12: =D12/C12 -> 0.85
B13: Search | C13: 20 | D13: =COUNTIF('Search'!G4:G23,"Pass") -> 18 | E13: =COUNTIF('Search'!G4:G23,"Fail") -> 2 | F13: =COUNTIF('Search'!G4:G23,"Blocked") -> 0 | G13: =D13/C13 -> 0.9
B14: Cart | C14: 20 | D14: =COUNTIF('Cart'!G4:G23,"Pass") -> 18 | E14: =COUNTIF('Cart'!G4:G23,"Fail") -> 2 | F14: =COUNTIF('Cart'!G4:G23,"Blocked") -> 0 | G14: =D14/C14 -> 0.9
B15: Checkout | C15: 20 | D15: =COUNTIF('Checkout'!G4:G23,"Pass") -> 18 | E15: =COUNTIF('Checkout'!G4:G23,"Fail") -> 2 | F15: =COUNTIF('Checkout'!G4:G23,"Blocked") -> 0 | G15: =D15/C15 -> 0.9
B16: User Interface | C16: 20 | D16: =COUNTIF('UI'!G4:G23,"Pass") -> 17 | E16: =COUNTIF('UI'!G4:G23,"Fail") -> 2 | F16: =COUNTIF('UI'!G4:G23,"Blocked") -> 1 | G16: =D16/C16 -> 0.85
B17: Total / Overall | C17: =SUM(C11:C16) -> 120 | D17: =SUM(D11:D16) -> 106 | E17: =SUM(E11:E16) -> 13 | F17: =SUM(F11:F16) -> 1 | G17: =D17/C17 -> 0.88333333
